libname/__init__.py
Topsis_1823-0.0.1.dist-info/METADATA
Topsis_1823-0.0.1.dist-info/WHEEL
Topsis_1823-0.0.1.dist-info/top_level.txt
Topsis_1823-0.0.1.dist-info/RECORD
