Metadata-Version: 2.1
Name: Topsis-1823
Version: 0.0.1
Summary: Topsis
Home-page: UNKNOWN
Author: Shriyanshi Agarwal
Author-email: <shriyanshi2301@gmail.com>
License: UNKNOWN
Keywords: topsis,python,model,best,test
Platform: UNKNOWN
Classifier: Development Status :: 1 - Planning
Classifier: Intended Audience :: Developers
Classifier: Programming Language :: Python :: 3
Classifier: Operating System :: Unix
Classifier: Operating System :: MacOS :: MacOS X
Classifier: Operating System :: Microsoft :: Windows
Requires-Dist: numpy
Requires-Dist: pandas
